<?xml version="1.0" encoding="UTF-8" standalone="yes"?>
<Root xmlns:xsi="http://www.w3.org/2001/XMLSchema-instance">
	<Row>
		<FieldType>Button</FieldType>
		<HeaderText>参照</HeaderText>
		<Width>30</Width>
		<HorizontalAlign>Center</HorizontalAlign>
		<Text></Text>
		<ValidationGroup></ValidationGroup>
		<CommandName>btnReference</CommandName>
		<ButtonType>Button</ButtonType>
	</Row>
	<Row>
		<FieldType>Button</FieldType>
		<HeaderText>更新</HeaderText>
		<Width>30</Width>
		<HorizontalAlign>Center</HorizontalAlign>
		<Text></Text>
		<ValidationGroup></ValidationGroup>
		<CommandName>btnUpdate</CommandName>
		<ButtonType>Button</ButtonType>
	</Row>
	<Row>
		<FieldType>Bound</FieldType>
		<HeaderText>TBOXID</HeaderText>
		<Width>60</Width>
		<HorizontalAlign></HorizontalAlign>
		<DataField>ＴＢＯＸＩＤ</DataField>
		<ReadOnly>1</ReadOnly>
		<Visible>1</Visible>
	</Row>
	<Row>
		<FieldType>Bound</FieldType>
		<HeaderText>ホール名</HeaderText>
		<Width>280</Width>
		<HorizontalAlign></HorizontalAlign>
		<DataField>ホール名</DataField>
		<ReadOnly>1</ReadOnly>
		<Visible>1</Visible>
	</Row>
	<Row>
		<FieldType>Bound</FieldType>
		<HeaderText>システム</HeaderText>
		<Width>80</Width>
		<HorizontalAlign></HorizontalAlign>
		<DataField>システム</DataField>
		<ReadOnly>1</ReadOnly>
		<Visible>1</Visible>
	</Row>
	<Row>
		<FieldType>Bound</FieldType>
		<HeaderText>工事依頼番号</HeaderText>
		<Width>100</Width>
		<HorizontalAlign></HorizontalAlign>
		<DataField>工事依頼番号</DataField>
		<ReadOnly>1</ReadOnly>
		<Visible>1</Visible>
	</Row>
	<Row>
		<FieldType>Bound</FieldType>
		<HeaderText>新規</HeaderText>
		<Width>60</Width>
		<HorizontalAlign>Center</HorizontalAlign>
		<DataField>工事種別_新規</DataField>
		<ReadOnly>1</ReadOnly>
		<Visible>1</Visible>
	</Row>
	<Row>
		<FieldType>Bound</FieldType>
		<HeaderText>増設</HeaderText>
		<Width>60</Width>
		<HorizontalAlign>Center</HorizontalAlign>
		<DataField>工事種別_増設</DataField>
		<ReadOnly>1</ReadOnly>
		<Visible>1</Visible>
	</Row>
	<Row>
		<FieldType>Bound</FieldType>
		<HeaderText>一部撤去</HeaderText>
		<Width>60</Width>
		<HorizontalAlign>Center</HorizontalAlign>
		<DataField>工事種別_一部撤去</DataField>
		<ReadOnly>1</ReadOnly>
		<Visible>1</Visible>
	</Row>
	<Row>
		<FieldType>Bound</FieldType>
		<HeaderText>店内移設</HeaderText>
		<Width>60</Width>
		<HorizontalAlign>Center</HorizontalAlign>
		<DataField>工事種別_移設</DataField>
		<ReadOnly>1</ReadOnly>
		<Visible>1</Visible>
	</Row>
	<Row>
		<FieldType>Bound</FieldType>
		<HeaderText>全撤去</HeaderText>
		<Width>60</Width>
		<HorizontalAlign>Center</HorizontalAlign>
		<DataField>工事種別_全撤去</DataField>
		<ReadOnly>1</ReadOnly>
		<Visible>1</Visible>
	</Row>
	<Row>
		<FieldType>Bound</FieldType>
		<HeaderText>一時撤去</HeaderText>
		<Width>60</Width>
		<HorizontalAlign>Center</HorizontalAlign>
		<DataField>工事種別_一時撤去</DataField>
		<ReadOnly>1</ReadOnly>
		<Visible>1</Visible>
	</Row>
	<Row>
		<FieldType>Bound</FieldType>
		<HeaderText>再設置</HeaderText>
		<Width>60</Width>
		<HorizontalAlign>Center</HorizontalAlign>
		<DataField>工事種別_再設置</DataField>
		<ReadOnly>1</ReadOnly>
		<Visible>1</Visible>
	</Row>
	<Row>
		<FieldType>Bound</FieldType>
		<HeaderText>構成変更</HeaderText>
		<Width>60</Width>
		<HorizontalAlign>Center</HorizontalAlign>
		<DataField>工事種別_構成変更</DataField>
		<ReadOnly>1</ReadOnly>
		<Visible>1</Visible>
	</Row>
	<Row>
		<FieldType>Bound</FieldType>
		<HeaderText>構成配信</HeaderText>
		<Width>60</Width>
		<HorizontalAlign>Center</HorizontalAlign>
		<DataField>工事種別_構成配信</DataField>
		<ReadOnly>1</ReadOnly>
		<Visible>1</Visible>
	</Row>
  <Row>
    <FieldType>Bound</FieldType>
    <HeaderText>ＶＵＰ</HeaderText>
    <Width>60</Width>
    <HorizontalAlign>Center</HorizontalAlign>
    <DataField>工事種別_ＶＵＰ</DataField>
    <ReadOnly>1</ReadOnly>
    <Visible>1</Visible>
  </Row>
  <Row>
    <FieldType>Bound</FieldType>
    <HeaderText>その他</HeaderText>
    <Width>60</Width>
    <HorizontalAlign>Center</HorizontalAlign>
    <DataField>工事種別_その他</DataField>
    <ReadOnly>1</ReadOnly>
    <Visible>1</Visible>
  </Row>
  <Row>
		<FieldType>Bound</FieldType>
		<HeaderText>工事日時</HeaderText>
		<Width>150</Width>
		<HorizontalAlign>Center</HorizontalAlign>
		<DataField>工事日時</DataField>
		<ReadOnly>1</ReadOnly>
		<Visible>1</Visible>
	</Row>
	<Row>
		<FieldType>Bound</FieldType>
		<HeaderText>連絡票管理番号</HeaderText>
		<Width></Width>
		<HorizontalAlign></HorizontalAlign>
		<DataField>連絡票管理番号</DataField>
		<ReadOnly>1</ReadOnly>
		<Visible>1</Visible>
	</Row>
	<Row>
		<FieldType>Bound</FieldType>
		<HeaderText></HeaderText>
		<Width></Width>
		<HorizontalAlign></HorizontalAlign>
		<DataField>東西フラグ</DataField>
		<ReadOnly>1</ReadOnly>
		<Visible>0</Visible>
	</Row>
	<Row>
		<FieldType>Bound</FieldType>
		<HeaderText></HeaderText>
		<Width></Width>
		<HorizontalAlign></HorizontalAlign>
		<DataField>ＩＤ／ＩＣ</DataField>
		<ReadOnly>1</ReadOnly>
		<Visible>0</Visible>
	</Row>
	<Row>
		<FieldType>Bound</FieldType>
		<HeaderText></HeaderText>
		<Width></Width>
		<HorizontalAlign></HorizontalAlign>
		<DataField>工事種別</DataField>
		<ReadOnly>1</ReadOnly>
		<Visible>0</Visible>
	</Row>
	<Row>
		<FieldType>Bound</FieldType>
		<HeaderText></HeaderText>
		<Width></Width>
		<HorizontalAlign></HorizontalAlign>
		<DataField>締月</DataField>
		<ReadOnly>1</ReadOnly>
		<Visible>0</Visible>
	</Row>
	<Row>
		<FieldType>Bound</FieldType>
		<HeaderText></HeaderText>
		<Width></Width>
		<HorizontalAlign></HorizontalAlign>
		<DataField>ホールコード</DataField>
		<ReadOnly>1</ReadOnly>
		<Visible>0</Visible>
	</Row>
	<Row>
		<FieldType>Bound</FieldType>
		<HeaderText></HeaderText>
		<Width></Width>
		<HorizontalAlign></HorizontalAlign>
		<DataField>現行システムコード</DataField>
		<ReadOnly>1</ReadOnly>
		<Visible>0</Visible>
	</Row>
	<Row>
		<FieldType>Bound</FieldType>
		<HeaderText></HeaderText>
		<Width></Width>
		<HorizontalAlign></HorizontalAlign>
		<DataField>現行システム</DataField>
		<ReadOnly>1</ReadOnly>
		<Visible>0</Visible>
	</Row>
	<Row>
		<FieldType>Bound</FieldType>
		<HeaderText></HeaderText>
		<Width></Width>
		<HorizontalAlign></HorizontalAlign>
		<DataField>工事日</DataField>
		<ReadOnly>1</ReadOnly>
		<Visible>0</Visible>
	</Row>
	<Row>
		<FieldType>Bound</FieldType>
		<HeaderText></HeaderText>
		<Width></Width>
		<HorizontalAlign></HorizontalAlign>
		<DataField>オープン日</DataField>
		<ReadOnly>1</ReadOnly>
		<Visible>0</Visible>
	</Row>
	<Row>
		<FieldType>Bound</FieldType>
		<HeaderText></HeaderText>
		<Width></Width>
		<HorizontalAlign></HorizontalAlign>
		<DataField>MTBOX機器費</DataField>
		<ReadOnly>1</ReadOnly>
		<Visible>0</Visible>
	</Row>
	<Row>
		<FieldType>Bound</FieldType>
		<HeaderText></HeaderText>
		<Width></Width>
		<HorizontalAlign></HorizontalAlign>
		<DataField>MLAN機器費</DataField>
		<ReadOnly>1</ReadOnly>
		<Visible>0</Visible>
	</Row>
	<Row>
		<FieldType>Bound</FieldType>
		<HeaderText></HeaderText>
		<Width></Width>
		<HorizontalAlign></HorizontalAlign>
		<DataField>M基本料金</DataField>
		<ReadOnly>1</ReadOnly>
		<Visible>0</Visible>
	</Row>
	<Row>
		<FieldType>Bound</FieldType>
		<HeaderText></HeaderText>
		<Width></Width>
		<HorizontalAlign></HorizontalAlign>
		<DataField>M工事費</DataField>
		<ReadOnly>1</ReadOnly>
		<Visible>0</Visible>
	</Row>
	<Row>
		<FieldType>Bound</FieldType>
		<HeaderText></HeaderText>
		<Width></Width>
		<HorizontalAlign></HorizontalAlign>
		<DataField>M材料費</DataField>
		<ReadOnly>1</ReadOnly>
		<Visible>0</Visible>
	</Row>
	<Row>
		<FieldType>Bound</FieldType>
		<HeaderText></HeaderText>
		<Width></Width>
		<HorizontalAlign></HorizontalAlign>
		<DataField>Mその他費用</DataField>
		<ReadOnly>1</ReadOnly>
		<Visible>0</Visible>
	</Row>
	<Row>
		<FieldType>Bound</FieldType>
		<HeaderText></HeaderText>
		<Width></Width>
		<HorizontalAlign></HorizontalAlign>
		<DataField>Mその他調整費</DataField>
		<ReadOnly>1</ReadOnly>
		<Visible>0</Visible>
	</Row>
	<Row>
		<FieldType>Bound</FieldType>
		<HeaderText></HeaderText>
		<Width></Width>
		<HorizontalAlign></HorizontalAlign>
		<DataField>Mカード受付関連費</DataField>
		<ReadOnly>1</ReadOnly>
		<Visible>0</Visible>
	</Row>
	<Row>
		<FieldType>Bound</FieldType>
		<HeaderText>工事料金</HeaderText>
		<Width></Width>
		<HorizontalAlign>Right</HorizontalAlign>
		<DataField>M合計</DataField>
		<ReadOnly>1</ReadOnly>
		<Visible>1</Visible>
	</Row>
	<Row>
		<FieldType>Bound</FieldType>
		<HeaderText></HeaderText>
		<Width></Width>
		<HorizontalAlign></HorizontalAlign>
		<DataField>M小計</DataField>
		<ReadOnly>1</ReadOnly>
		<Visible>0</Visible>
	</Row>
	<Row>
		<FieldType>Bound</FieldType>
		<HeaderText></HeaderText>
		<Width></Width>
		<HorizontalAlign></HorizontalAlign>
		<DataField>会社名</DataField>
		<ReadOnly>1</ReadOnly>
		<Visible>0</Visible>
	</Row>
	<Row>
		<FieldType>Bound</FieldType>
		<HeaderText></HeaderText>
		<Width></Width>
		<HorizontalAlign></HorizontalAlign>
		<DataField>連番</DataField>
		<ReadOnly>1</ReadOnly>
		<Visible>0</Visible>
	</Row>
	<Row>
		<FieldType>Bound</FieldType>
		<HeaderText></HeaderText>
		<Width></Width>
		<HorizontalAlign></HorizontalAlign>
		<DataField>改ページ</DataField>
		<ReadOnly>1</ReadOnly>
		<Visible>0</Visible>
	</Row>
</Root>
