<?xml version="1.0" encoding="UTF-8" standalone="yes"?>
<Root xmlns:xsi="http://www.w3.org/2001/XMLSchema-instance">
	<Row>
		<FieldType>Button</FieldType>
		<HeaderText>参照</HeaderText>
		<Width>30</Width>
		<HorizontalAlign>Center</HorizontalAlign>
		<Text>  </Text>
		<ValidationGroup></ValidationGroup>
		<CommandName>btnReference</CommandName>
		<ButtonType>Button</ButtonType>
	</Row>
	<Row>
		<FieldType>Button</FieldType>
		<HeaderText>更新</HeaderText>
		<Width>30</Width>
		<HorizontalAlign>Center</HorizontalAlign>
		<Text>  </Text>
		<ValidationGroup></ValidationGroup>
		<CommandName>btnUpdate</CommandName>
		<ButtonType>Button</ButtonType>
	</Row>
	<Row>
		<FieldType>Bound</FieldType>
		<HeaderText>設置区分</HeaderText>
		<Width>30</Width>
		<HorizontalAlign>Center</HorizontalAlign>
		<DataField>設置区分</DataField>
		<ReadOnly>1</ReadOnly>
		<Visible>1</Visible>
	</Row>
	<Row>
		<FieldType>Bound</FieldType>
		<HeaderText>実施日時</HeaderText>
		<Width>90</Width>
		<HorizontalAlign>Center</HorizontalAlign>
		<DataField>実施日時</DataField>
		<ReadOnly>1</ReadOnly>
		<Visible>1</Visible>
	</Row>
	<Row>
		<FieldType>Bound</FieldType>
		<HeaderText>ＴＢＯＸＩＤ</HeaderText>
		<Width>75</Width>
		<HorizontalAlign>Center</HorizontalAlign>
		<DataField>ＴＢＯＸＩＤ</DataField>
		<ReadOnly>1</ReadOnly>
		<Visible>1</Visible>
	</Row>
	<Row>
		<FieldType>Bound</FieldType>
		<HeaderText>工事依頼番号</HeaderText>
		<Width>115</Width>
		<HorizontalAlign>Center</HorizontalAlign>
		<DataField>工事依頼番号</DataField>
		<ReadOnly>1</ReadOnly>
		<Visible>1</Visible>
	</Row>
	<Row>
		<FieldType>Bound</FieldType>
		<HeaderText>ホール名</HeaderText>
		<Width>160</Width>
		<HorizontalAlign>Left</HorizontalAlign>
		<DataField>ホール名</DataField>
		<ReadOnly>1</ReadOnly>
		<Visible>1</Visible>
	</Row>
	<Row>
		<FieldType>Bound</FieldType>
		<HeaderText>状況</HeaderText>
		<Width>80</Width>
		<HorizontalAlign>Center</HorizontalAlign>
		<DataField>状況</DataField>
		<ReadOnly>1</ReadOnly>
		<Visible>1</Visible>
	</Row>
	<Row>
		<FieldType>Bound</FieldType>
		<HeaderText>都道府県名</HeaderText>
		<Width>80</Width>
		<HorizontalAlign>Center</HorizontalAlign>
		<DataField>都道府県名</DataField>
		<ReadOnly>1</ReadOnly>
		<Visible>1</Visible>
	</Row>
	<Row>
		<FieldType>Bound</FieldType>
		<HeaderText>システム</HeaderText>
		<Width>70</Width>
		<HorizontalAlign>Center</HorizontalAlign>
		<DataField>システム</DataField>
		<ReadOnly>1</ReadOnly>
		<Visible>1</Visible>
	</Row>
	<Row>
		<FieldType>Bound</FieldType>
		<HeaderText>新規</HeaderText>
		<Width>30</Width>
		<HorizontalAlign>Center</HorizontalAlign>
		<DataField>工事種別_新規</DataField>
		<ReadOnly>1</ReadOnly>
		<Visible>1</Visible>
	</Row>
	<Row>
		<FieldType>Bound</FieldType>
		<HeaderText>増設</HeaderText>
		<Width>30</Width>
		<HorizontalAlign>Center</HorizontalAlign>
		<DataField>工事種別_増設</DataField>
		<ReadOnly>1</ReadOnly>
		<Visible>1</Visible>
	</Row>
	<Row>
		<FieldType>Bound</FieldType>
		<HeaderText>一部撤去</HeaderText>
		<Width>30</Width>
		<HorizontalAlign>Center</HorizontalAlign>
		<DataField>工事種別_一部撤去</DataField>
		<ReadOnly>1</ReadOnly>
		<Visible>1</Visible>
	</Row>
	<Row>
		<FieldType>Bound</FieldType>
		<HeaderText>移設</HeaderText>
		<Width>30</Width>
		<HorizontalAlign>Center</HorizontalAlign>
		<DataField>工事種別_移設</DataField>
		<ReadOnly>1</ReadOnly>
		<Visible>1</Visible>
	</Row>
	<Row>
		<FieldType>Bound</FieldType>
		<HeaderText>全撤去</HeaderText>
		<Width>30</Width>
		<HorizontalAlign>Center</HorizontalAlign>
		<DataField>工事種別_全撤去</DataField>
		<ReadOnly>1</ReadOnly>
		<Visible>1</Visible>
	</Row>
	<Row>
		<FieldType>Bound</FieldType>
		<HeaderText>一時撤去</HeaderText>
		<Width>30</Width>
		<HorizontalAlign>Center</HorizontalAlign>
		<DataField>工事種別_一時撤去</DataField>
		<ReadOnly>1</ReadOnly>
		<Visible>1</Visible>
	</Row>
	<Row>
		<FieldType>Bound</FieldType>
		<HeaderText>再設置</HeaderText>
		<Width>30</Width>
		<HorizontalAlign>Center</HorizontalAlign>
		<DataField>工事種別_再設置</DataField>
		<ReadOnly>1</ReadOnly>
		<Visible>1</Visible>
	</Row>
	<Row>
		<FieldType>Bound</FieldType>
		<HeaderText>構成変更</HeaderText>
		<Width>30</Width>
		<HorizontalAlign>Center</HorizontalAlign>
		<DataField>工事種別_構成変更</DataField>
		<ReadOnly>1</ReadOnly>
		<Visible>1</Visible>
	</Row>
	<Row>
		<FieldType>Bound</FieldType>
		<HeaderText>構成配信</HeaderText>
		<Width>30</Width>
		<HorizontalAlign>Center</HorizontalAlign>
		<DataField>工事種別_構成配信</DataField>
		<ReadOnly>1</ReadOnly>
		<Visible>1</Visible>
	</Row>
	<Row>
		<FieldType>Bound</FieldType>
		<HeaderText>VERUP</HeaderText>
		<Width>30</Width>
		<HorizontalAlign>Center</HorizontalAlign>
		<DataField>VERUP</DataField>
		<ReadOnly>1</ReadOnly>
		<Visible>1</Visible>
	</Row>
  <Row>
    <FieldType>Bound</FieldType>
    <HeaderText>その他</HeaderText>
    <Width>95</Width>
    <HorizontalAlign>Center</HorizontalAlign>
    <DataField>工事種別_その他</DataField>
    <ReadOnly>1</ReadOnly>
    <Visible>1</Visible>
  </Row>
  <Row>
    <FieldType>Bound</FieldType>
    <HeaderText>発生工事全</HeaderText>
    <Width>45</Width>
    <HorizontalAlign>Center</HorizontalAlign>
    <DataField>発生工事全</DataField>
    <ReadOnly>1</ReadOnly>
    <Visible>1</Visible>
  </Row>
  <Row>
    <FieldType>Bound</FieldType>
    <HeaderText>工事遅延</HeaderText>
    <Width>45</Width>
    <HorizontalAlign>Center</HorizontalAlign>
    <DataField>工事遅延</DataField>
    <ReadOnly>1</ReadOnly>
    <Visible>1</Visible>
  </Row>
  <Row>
    <FieldType>Bound</FieldType>
    <HeaderText>予備機使用</HeaderText>
    <Width>45</Width>
    <HorizontalAlign>Center</HorizontalAlign>
    <DataField>予備機使用</DataField>
    <ReadOnly>1</ReadOnly>
    <Visible>1</Visible>
  </Row>
  <Row>
    <FieldType>Bound</FieldType>
    <HeaderText>空振り工事</HeaderText>
    <Width>45</Width>
    <HorizontalAlign>Center</HorizontalAlign>
    <DataField>空振り工事</DataField>
    <ReadOnly>1</ReadOnly>
    <Visible>1</Visible>
  </Row>
  <Row>
    <FieldType>Bound</FieldType>
    <HeaderText>INS</HeaderText>
    <Width>30</Width>
    <HorizontalAlign>Center</HorizontalAlign>
    <DataField>INS</DataField>
    <ReadOnly>1</ReadOnly>
    <Visible>1</Visible>
  </Row>
  <Row>
    <FieldType>Bound</FieldType>
    <HeaderText>TEL</HeaderText>
    <Width>30</Width>
    <HorizontalAlign>Center</HorizontalAlign>
    <DataField>TEL</DataField>
    <ReadOnly>1</ReadOnly>
    <Visible>1</Visible>
  </Row>
  <Row>
    <FieldType>Bound</FieldType>
    <HeaderText>その他</HeaderText>
    <Width>30</Width>
    <HorizontalAlign>Center</HorizontalAlign>
    <DataField>その他</DataField>
    <ReadOnly>1</ReadOnly>
    <Visible>1</Visible>
  </Row>
  <Row>
    <FieldType>Bound</FieldType>
    <HeaderText>構成</HeaderText>
    <Width>30</Width>
    <HorizontalAlign>Center</HorizontalAlign>
    <DataField>構成</DataField>
    <ReadOnly>1</ReadOnly>
    <Visible>1</Visible>
  </Row>
  <!--<Row>
		<FieldType>Bound</FieldType>
		<HeaderText>削除</HeaderText>
		<Width>30</Width>
		<HorizontalAlign>Center</HorizontalAlign>
		<DataField>削除有無</DataField>
		<ReadOnly>1</ReadOnly>
		<Visible>1</Visible>
	</Row>-->
  <Row>
		<FieldType>Bound</FieldType>
		<HeaderText>設置区分コード</HeaderText>
		<Width>100</Width>
		<HorizontalAlign></HorizontalAlign>
		<DataField>設置区分コード</DataField>
		<ReadOnly>1</ReadOnly>
		<Visible>0</Visible>
	</Row>
  <Row>
    <FieldType>Bound</FieldType>
    <HeaderText>最大進捗</HeaderText>
    <Width>200</Width>
    <HorizontalAlign></HorizontalAlign>
    <DataField>最大進捗</DataField>
    <ReadOnly>1</ReadOnly>
    <Visible>0</Visible>
  </Row>
  <Row>
    <FieldType>Bound</FieldType>
    <HeaderText>都道府県コード</HeaderText>
    <Width>60</Width>
    <HorizontalAlign>Center</HorizontalAlign>
    <DataField>都道府県コード</DataField>
    <ReadOnly>1</ReadOnly>
    <Visible>0</Visible>
  </Row>
  <Row>
    <FieldType>Bound</FieldType>
    <HeaderText>双子区分</HeaderText>
    <Width>0</Width>
    <HorizontalAlign>Center</HorizontalAlign>
    <DataField>双子区分</DataField>
    <ReadOnly>1</ReadOnly>
    <Visible>0</Visible>
  </Row>
</Root>
